vivaldi_feed_exporter/__init__.py
vivaldi_feed_exporter/main.py
vivaldi_feed_exporter/opml.py
vivaldi_feed_exporter-0.1.0.dist-info/entry_points.txt
vivaldi_feed_exporter-0.1.0.dist-info/LICENSE
vivaldi_feed_exporter-0.1.0.dist-info/WHEEL
vivaldi_feed_exporter-0.1.0.dist-info/METADATA
vivaldi_feed_exporter-0.1.0.dist-info/RECORD
