Metadata-Version: 2.1
Name: vivaldi-feed-exporter
Version: 0.1.0
Summary: A command line tool to export feeds from Vivaldi as OPML
Home-page: https://github.com/a-takahashi223/vivaldi-feed-exporter
License: MIT
Author: Akira Takahashi
Author-email: pretty.audience.64b9de@gizmotik.com
Requires-Python: >=3.10,<4.0
Classifier: License :: OSI Approved :: MIT License
Classifier: Programming Language :: Python :: 3
Classifier: Programming Language :: Python :: 3.10
Requires-Dist: opyml (>=0.1.1,<0.2.0)
Project-URL: Repository, https://github.com/a-takahashi223/vivaldi-feed-exporter
